setup.py
udc_distributions/Binomialdistribution.py
udc_distributions/Gaussiandistribution.py
udc_distributions/Generaldistribution.py
udc_distributions/__init__.py
udc_distributions.egg-info/PKG-INFO
udc_distributions.egg-info/SOURCES.txt
udc_distributions.egg-info/dependency_links.txt
udc_distributions.egg-info/not-zip-safe
udc_distributions.egg-info/top_level.txt