Metadata-Version: 1.0
Name: udc-distributions
Version: 0.1
Summary: Vince UDC Gaussian distributions Practice
Home-page: UNKNOWN
Author: UNKNOWN
Author-email: UNKNOWN
License: UNKNOWN
Platform: UNKNOWN
